ml4cps/__init__.py
ml4cps/tools.py
ml4cps/vis.py
ml4cps/automata/__init__.py
ml4cps/automata/base.py
ml4cps/automata/learn.py
ml4cps/control/__init__.py
ml4cps/control/base.py
ml4cps/cps/__init__.py
ml4cps/cps/base.py
ml4cps/cps/decisions.py
ml4cps/cps/sim.py
ml4cps/denta/__init__.py
ml4cps/denta/base.py
ml4cps/denta/denta_tools.py
ml4cps/discretization/__init__.py
ml4cps/discretization/discretization.py
ml4cps/examples/__init__.py
ml4cps/examples/examples.py
ml4cps/log_analysis/__init__.py
ml4cps/log_analysis/log_compare_tool.py
ml4cps/nn/__init__.py
ml4cps/nn/rbm.py
ml4cps/reconfig/__init__.py
ml4cps/reconfig/reconfig.py
ml4cps-0.1.192.dist-info/licenses/LICENSE
ml4cps-0.1.192.dist-info/METADATA
ml4cps-0.1.192.dist-info/WHEEL
ml4cps-0.1.192.dist-info/top_level.txt
ml4cps-0.1.192.dist-info/RECORD
