Metadata-Version: 2.4
Name: ml4cps
Version: 0.1.192
Summary: Tools for learning, plotting, analyzing etc. of discrete, continuous, timed, and hybrid cyber-physical systems.
Home-page: https://github.com/ai4cps-com/ml4cps
Author: Nemanja Hranisavljevic & Tom Westermann
Author-email: nemanja@ai4cps.com
Classifier: Programming Language :: Python :: 3
Classifier: License :: OSI Approved :: MIT License
Classifier: Operating System :: OS Independent
Requires-Python: >=3.6
License-File: LICENSE
Requires-Dist: dash
Requires-Dist: pandas
Requires-Dist: networkx
Requires-Dist: plotly
Requires-Dist: numpy
Requires-Dist: dash_daq
Requires-Dist: dash-bootstrap-components
Requires-Dist: pydotplus
Requires-Dist: dash-cytoscape
Requires-Dist: simpy
Requires-Dist: mlflow
Requires-Dist: torch
Requires-Dist: z3-solver
Requires-Dist: scipy
Requires-Dist: sphinx
Requires-Dist: matplotlib
Requires-Dist: scikit-learn
Requires-Dist: fastdtw
Requires-Dist: openai
Requires-Dist: loguru
Requires-Dist: regex
Requires-Dist: Levenshtein
Requires-Dist: tqdm
Requires-Dist: gymnasium
Dynamic: author
Dynamic: author-email
Dynamic: classifier
Dynamic: home-page
Dynamic: license-file
Dynamic: requires-dist
Dynamic: requires-python
Dynamic: summary
